proloaf/__init__.py
proloaf/baselinehandler.py
proloaf/cli.py
proloaf/confighandler.py
proloaf/datahandler.py
proloaf/loghandler.py
proloaf/metrics.py
proloaf/modelhandler.py
proloaf/models.py
proloaf/plot.py
proloaf/tensorloader.py
proloaf-0.2.0.dist-info/LICENSE
proloaf-0.2.0.dist-info/METADATA
proloaf-0.2.0.dist-info/WHEEL
proloaf-0.2.0.dist-info/top_level.txt
proloaf-0.2.0.dist-info/RECORD
