Metadata-Version: 2.1
Name: proloaf
Version: 0.2.0
Summary: A Probabilistic Load Forecasting Project.
Home-page: https://github.com/sogno-platform/proloaf
Author: Gonca Gürses-Tran
Author-email: gguerses@eonerc.rwth-aachen.de
License: Apache License 2.0
Platform: UNKNOWN
Classifier: Topic :: Scientific/Engineering
Classifier: License :: OSI Approved :: Apache Software License
Classifier: Operating System :: OS Independent
Classifier: Programming Language :: Python :: 3.8
Requires-Python: >=3.8
License-File: LICENSE
Requires-Dist: numpy
Requires-Dist: pandas
Requires-Dist: matplotlib
Requires-Dist: torch
Requires-Dist: scikit-learn
Requires-Dist: datetime
Requires-Dist: pyparsing (<3,>=2.2.1)
Requires-Dist: arch
Requires-Dist: optuna
Requires-Dist: pmdarima
Requires-Dist: statsmodels
Requires-Dist: tensorboard
